atlas_i2c/__init__.py
atlas_i2c/atlas_i2c.py
atlas_i2c/commands.py
atlas_i2c/constants.py
atlas_i2c/sensors.py
atlas_i2c/version.py
atlas_i2c-0.3.1.dist-info/LICENSE
atlas_i2c-0.3.1.dist-info/METADATA
atlas_i2c-0.3.1.dist-info/WHEEL
atlas_i2c-0.3.1.dist-info/top_level.txt
atlas_i2c-0.3.1.dist-info/RECORD
