Metadata-Version: 2.1
Name: atlas-i2c
Version: 0.3.1
Summary: Atlas I2C
Home-page: https://github.com/timboring/atlas_i2c
Author: Tim Boring
Author-email: tim@boring.green
License: UNKNOWN
Platform: UNKNOWN
Requires-Python: >=3.6
